[
        {
            "attribute": "SSN",
            "type": "varchar",
            "unique": true,
            "indexName": "Employee_SSN",
            "selectivity": 0.033333333,
            "selectionCardinality": 1,
            "NDV": 30
        },
        {
            "attribute": "Fname",
            "type": "varchar",
            "unique": false,
            "indexName": "Employee_fname",
            "selectivity": 0.038461538,
            "selectionCardinality": 1.153846154,
            "NDV": 26
        },
        {
            "attribute": "Minit",
            "type": "char",
            "unique": false,
            "indexName": null,
            "selectivity": 0.111111111,
            "selectionCardinality": 3.333333333,
            "NDV": 9
        },
        {
            "attribute": "Lname",
            "type": "varchar",
            "unique": false,
            "indexName": "Employee_lname",
            "selectivity": 0.043478261,
            "selectionCardinality": 1.304347826,
            "NDV": 23
        },
        {
            "attribute": "DOB",
            "type": "date",
            "unique": false,
            "indexName": null,
            "selectivity": 0.037037037,
            "selectionCardinality": 1.111111111,
            "NDV": 27
        },
        {
            "attribute": "Address",
            "type": "varchar",
            "unique": false,
            "indexName": null,
            "selectivity": 0.045454545,
            "selectionCardinality": 1.363636364,
            "NDV": 22
        },
        {
            "attribute": "Gender",
            "type": "enum",
            "unique": false,
            "indexName": "Employee_gender",
            "selectivity": 0.5,
            "selectionCardinality": 15,
            "NDV": 2
        },
        {
            "attribute": "PhoneNo",
            "type": "varchar",
            "unique": false,
            "indexName": null,
            "selectivity": 0.066666667,
            "selectionCardinality": 2,
            "NDV": 15
        },
        {
            "attribute": "HireDate",
            "type": "date",
            "unique": false,
            "indexName": null,
            "selectivity": 0.037037037,
            "selectionCardinality": 1.111111111,
            "NDV": 27
        },
        {
            "attribute": "Manager",
            "type": "tinyint",
            "unique": false,
            "indexName": "Employee_manager",
            "selectivity": 0.5,
            "selectionCardinality": 15,
            "NDV": 2
        },
        {
            "attribute": "ManagerSSN",
            "type": "varchar",
            "unique": false,
            "indexName": "Employee_managerSSN",
            "selectivity": 0.333333333,
            "selectionCardinality": 10,
            "NDV": 3
        }
]

